easy_sqlite3/__init__.py
easy_sqlite3-0.0.2.dist-info/LICENSE.txt
easy_sqlite3-0.0.2.dist-info/METADATA
easy_sqlite3-0.0.2.dist-info/WHEEL
easy_sqlite3-0.0.2.dist-info/top_level.txt
easy_sqlite3-0.0.2.dist-info/RECORD
